imagetitle/__init__.py
imagetitle/__main__.py
imagetitle/imagetitle.py
imagetitle-0.0.1.dist-info/entry_points.txt
imagetitle-0.0.1.dist-info/WHEEL
imagetitle-0.0.1.dist-info/METADATA
imagetitle-0.0.1.dist-info/RECORD
