Metadata-Version: 2.1
Name: imagetitle
Version: 0.0.1
Summary:  Overlay image, top, bottom, left or right, with a title.
Home-page: https://rnwolf.github.io/imagetitle/
License: MIT
Keywords: Image,CLI,Title,Annotate
Author: Rudiger Wolf
Author-email: Rudiger.Wolf@ThroughputFocus.com
Requires-Python: >=3.8,<4.0
Classifier: Development Status :: 3 - Alpha
Classifier: Intended Audience :: Developers
Classifier: License :: OSI Approved :: MIT License
Classifier: Operating System :: OS Independent
Classifier: Programming Language :: Python :: 3
Classifier: Programming Language :: Python :: 3.8
Classifier: Topic :: Software Development :: Libraries :: Python Modules
Requires-Dist: Pillow (>=7.1.2,<8.0.0)
Requires-Dist: dynaconf (>=3.0.0rc1,<4.0.0)
Requires-Dist: filetype (>=1.0.7,<2.0.0)
Requires-Dist: importlib_metadata (>=1.6.0,<2.0.0); python_version < "3.8"
Requires-Dist: typer[all] (>=0.2.1,<0.3.0)
Project-URL: Repository, https://github.com/rnwolf/overlay_image_title
